psslib/psslib.py
psslib-0.0.1.dist-info/DESCRIPTION.rst
psslib-0.0.1.dist-info/METADATA
psslib-0.0.1.dist-info/RECORD
psslib-0.0.1.dist-info/WHEEL
psslib-0.0.1.dist-info/metadata.json
psslib-0.0.1.dist-info/top_level.txt
