Metadata-Version: 2.0
Name: psslib
Version: 0.0.1
Summary: pss (python system securty) An Securty utility
Home-page: https://brainlog.yolasite.com/
Author: Yaya Souno Qurashi
Author-email: umarmoiz2010@gmail.com
License: Apache2
Platform: UNKNOWN
